FoxDotCC/__init__.py
foxdotcc-0.1.2.dist-info/METADATA
foxdotcc-0.1.2.dist-info/WHEEL
foxdotcc-0.1.2.dist-info/licenses/LICENSE
foxdotcc-0.1.2.dist-info/RECORD
